branesta/__init__.py
branesta/branesta.py
branesta/cli.py
branesta-0.1.7.dist-info/AUTHORS.rst
branesta-0.1.7.dist-info/LICENSE
branesta-0.1.7.dist-info/METADATA
branesta-0.1.7.dist-info/WHEEL
branesta-0.1.7.dist-info/entry_points.txt
branesta-0.1.7.dist-info/top_level.txt
branesta-0.1.7.dist-info/RECORD
