Metadata-Version: 2.1
Name: branesta
Version: 0.1.7
Summary: Tool for computing brain network stability, a biomarker for brain aging.
Home-page: https://github.com/BotondA/branesta
Author: Botond Antal
Author-email: botond.antal@stonybrook.edu
License: MIT license
Keywords: branesta
Platform: UNKNOWN
Classifier: Development Status :: 2 - Pre-Alpha
Classifier: Intended Audience :: Developers
Classifier: License :: OSI Approved :: MIT License
Classifier: Natural Language :: English
Classifier: Programming Language :: Python :: 3
Classifier: Programming Language :: Python :: 3.5
Classifier: Programming Language :: Python :: 3.6
Classifier: Programming Language :: Python :: 3.7
Classifier: Programming Language :: Python :: 3.8
Requires-Python: >=3.5
Requires-Dist: numpy
Requires-Dist: pandas
Requires-Dist: nilearn
